nonebot_plugin_pxchat/__init__.py
nonebot_plugin_pxchat/chat.py
nonebot_plugin_pxchat/commands.py
nonebot_plugin_pxchat/config.py
nonebot_plugin_pxchat/context.py
nonebot_plugin_pxchat/image2txt.py
nonebot_plugin_pxchat/manager.py
nonebot_plugin_pxchat/mcp_manager.py
nonebot_plugin_pxchat/send2root.py
nonebot_plugin_pxchat-1.0.3.dist-info/WHEEL
nonebot_plugin_pxchat-1.0.3.dist-info/METADATA
nonebot_plugin_pxchat-1.0.3.dist-info/RECORD
