Metadata-Version: 2.3
Name: nonebot-plugin-pxchat
Version: 1.0.3
Summary: 基于AI大模型的聊天机器人，支持大模型api任意切换、上下文记忆、群聊智能参与、图片识别、MCP等功能
Author: whopxx
Author-email: whopxx <2074447320@qq.com>
Requires-Dist: nonebot2>=2.4.3,<3.0.0
Requires-Dist: nonebot-adapter-onebot>=2.4.6,<3.0.0
Requires-Dist: openai>=2.2.0
Requires-Dist: mcp>=1.16.0
Requires-Dist: nonebot-plugin-localstore>=0.7.3
Requires-Python: >=3.10
Project-URL: Repository, https://github.com/whopxxx/nonebot-plugin-pxchat
